numfolio/__init__.py
numfolio/core.py
numfolio/stats/__init__.py
numfolio/stats/_stats.py
numfolio/stats/reward.py
numfolio/stats/risk.py
numfolio/stats/risk_adjusted_reward.py
numfolio-0.1.1.dist-info/licenses/LICENSE
numfolio-0.1.1.dist-info/METADATA
numfolio-0.1.1.dist-info/WHEEL
numfolio-0.1.1.dist-info/top_level.txt
numfolio-0.1.1.dist-info/RECORD
