Metadata-Version: 2.4
Name: numfolio
Version: 0.1.1
Author-email: agdiiura <andreadiiura@gmail.com>
License: MIT License
Project-URL: Homepage, https://github.com/agdiiura/numfolio
Project-URL: Documentation, https://numfolio.readthedocs.io/en/stable/index.html
Project-URL: Repository, https://github.com/agdiiura/numfolio.git
License-File: LICENSE
Requires-Dist: joblib>=1.3.2
Requires-Dist: pandas>=2.2.1
Requires-Dist: numpy>=1.22
Requires-Dist: scikit-learn>=1.5.0
Requires-Dist: scipy>=1.12.0
Requires-Dist: arch>=6.3.0
Requires-Dist: numba>0.59.0
Provides-Extra: build
Requires-Dist: ruff>=0.11.0; extra == "build"
Requires-Dist: colorama>=0.4.6; extra == "build"
Requires-Dist: coverage>=7.0; extra == "build"
Requires-Dist: isort>=6.0.0; extra == "build"
Requires-Dist: pre-commit>=4.0.0; extra == "build"
Requires-Dist: setuptools-git-versioning>=1.13.4; extra == "build"
Requires-Dist: unittest-xml-reporting>=3.2.0; extra == "build"
Provides-Extra: docs
Requires-Dist: mkdocs>=1.6.0; extra == "docs"
Requires-Dist: mkdocstrings[python]==0.30.0; extra == "docs"
Dynamic: license-file
